bankline_direct_parser-0.9.dist-info/licenses/LICENSE.txt
bankline_parser/__init__.py
bankline_parser/data_services/__init__.py
bankline_parser/data_services/enums.py
bankline_parser/data_services/exceptions.py
bankline_parser/data_services/fields.py
bankline_parser/data_services/models.py
bankline_parser/data_services/parser.py
bankline_parser/data_services/utils.py
bankline_direct_parser-0.9.dist-info/METADATA
bankline_direct_parser-0.9.dist-info/WHEEL
bankline_direct_parser-0.9.dist-info/top_level.txt
bankline_direct_parser-0.9.dist-info/RECORD
