Metadata-Version: 2.4
Name: bankline-direct-parser
Version: 0.9
Summary: Parser for Bankline Direct banking information services
Home-page: https://github.com/ministryofjustice/bankline-direct-parser
Author: Ministry of Justice Digital & Technology
Author-email: dev@digital.justice.gov.uk
License: MIT
Keywords: bankline
Classifier: Development Status :: 4 - Beta
Classifier: Intended Audience :: Developers
Classifier: License :: OSI Approved :: MIT License
Classifier: Natural Language :: English
Classifier: Operating System :: OS Independent
Classifier: Programming Language :: Python :: 3
Classifier: Programming Language :: Python :: 3 :: Only
Classifier: Programming Language :: Python :: 3.10
Classifier: Programming Language :: Python :: 3.11
Classifier: Programming Language :: Python :: 3.12
Classifier: Programming Language :: Python :: 3.13
Classifier: Programming Language :: Python :: 3.14
Classifier: Topic :: Software Development :: Libraries :: Python Modules
Requires-Python: >=3.6
License-File: LICENSE.txt
Dynamic: license-file
